LLMPrompts/LLMPrompts.py
LLMPrompts/__init__.py
LLMPrompts/resources/prompts.json
llmprompts-0.1.5.dist-info/licenses/LICENSE
llmprompts-0.1.5.dist-info/METADATA
llmprompts-0.1.5.dist-info/WHEEL
llmprompts-0.1.5.dist-info/top_level.txt
llmprompts-0.1.5.dist-info/RECORD
