Metadata-Version: 2.4
Name: LLMPrompts
Version: 0.1.5
Summary: Facilitating the creation, storage, retrieval, and curation of LLM prompts.
Home-page: https://github.com/antononcube/Python-packages/tree/main/LLMPrompts
Author: Anton Antonov
Author-email: antononcube@posteo.net
License: BSD-3-Clause
Keywords: openai,chatgpt,palm,prompt,prompts,large language model,large language models,llm,llm prompt,llm prompts
Classifier: Intended Audience :: Science/Research
Classifier: Intended Audience :: Developers
Classifier: Programming Language :: Python :: 3
Classifier: Intended Audience :: Science/Research
Classifier: Intended Audience :: Developers
Classifier: Operating System :: OS Independent
Requires-Python: >=3.7
License-File: LICENSE
Dynamic: author
Dynamic: author-email
Dynamic: classifier
Dynamic: description
Dynamic: description-content-type
Dynamic: home-page
Dynamic: keywords
Dynamic: license
Dynamic: license-file
Dynamic: requires-python
Dynamic: summary
